PyDSlog/__init__.py
PyDSlog/classificator/SignalClassificator.py
PyDSlog/classificator/__init__.py
PyDSlog/crc8/__init__.py
PyDSlog/crc8/crc8.py
PyDSlog/csv/ArduinoLogger.py
PyDSlog/csv/IO5640Logger.py
PyDSlog/csv/MLS160ALogger.py
PyDSlog/csv/MQTTLogger.py
PyDSlog/csv/__init__.py
PyDSlog/stream/AMG883Stream.py
PyDSlog/stream/ArduinoStream.py
PyDSlog/stream/IO5640Stream.py
PyDSlog/stream/MLS160AStream.py
PyDSlog/stream/MQTTStream.py
PyDSlog/stream/STMStream.py
PyDSlog/stream/__init__.py
PyDSlog/transform/__init__.py
PyDSlog/transform/fft.py
PyDSlog-0.0.7.dist-info/LICENSE
PyDSlog-0.0.7.dist-info/METADATA
PyDSlog-0.0.7.dist-info/WHEEL
PyDSlog-0.0.7.dist-info/top_level.txt
PyDSlog-0.0.7.dist-info/RECORD
