Metadata-Version: 2.1
Name: PyDSlog
Version: 0.0.7
Summary: Sensor data acquisition library.
Home-page: https://github.com/fbussv/PyDSlog
Author: SSV Software Systems GmbH
Author-email: fbu@ssv-embedded.de
License: UNKNOWN
Platform: UNKNOWN
Classifier: Programming Language :: Python :: 3
Classifier: License :: OSI Approved :: MIT License
Classifier: Operating System :: OS Independent
Requires-Dist: pyserial
Requires-Dist: paho-mqtt
